const/__init__.py
const/const.py
const-type/__init__.py
const-type/const.py
pyConstant/__init__.py
pyConstant/const.py
const_type-1.0.3.dist-info/METADATA
const_type-1.0.3.dist-info/WHEEL
const_type-1.0.3.dist-info/top_level.txt
const_type-1.0.3.dist-info/RECORD
