Metadata-Version: 2.1
Name: const-type
Version: 1.0.3
Summary: Const type for python
Author: kronus-lx (Joel Manning)
Author-email: joelem2@hotmail.com
Keywords: python,constants,const
Classifier: Development Status :: 1 - Planning
Classifier: Intended Audience :: Developers
Classifier: Programming Language :: Python :: 3
Classifier: Operating System :: Unix
Classifier: Operating System :: MacOS :: MacOS X
Classifier: Operating System :: Microsoft :: Windows
